container_manager/__init__.py
container_manager/coctl.py
container_manager-0.1.0.dist-info/METADATA
container_manager-0.1.0.dist-info/WHEEL
container_manager-0.1.0.dist-info/entry_points.txt
container_manager-0.1.0.dist-info/top_level.txt
container_manager-0.1.0.dist-info/RECORD
