Metadata-Version: 2.1
Name: container-manager
Version: 0.1.0
Summary: Container manager
Home-page: https://github.com/YujiOshima/container_manager
Author: YujiOshima
Author-email: yuji.oshima0x3fd@gmail.com
Maintainer: YujiOshima
Maintainer-email: yuji.oshima0x3fd@gmail.com
License: MIT
Platform: UNKNOWN
Classifier: Programming Language :: Python :: 3
Classifier: License :: OSI Approved :: MIT License
Classifier: Operating System :: OS Independent
Requires-Python: >=3.7
Requires-Dist: docker-py
